pyadrc/__init__.py
pyadrc/models.py
pyadrc/pyadrc.py
pyadrc-0.4.1.dist-info/AUTHORS.rst
pyadrc-0.4.1.dist-info/LICENSE
pyadrc-0.4.1.dist-info/METADATA
pyadrc-0.4.1.dist-info/WHEEL
pyadrc-0.4.1.dist-info/top_level.txt
pyadrc-0.4.1.dist-info/RECORD
