Metadata-Version: 2.1
Name: pyadrc
Version: 0.4.1
Summary: Active Disturbance Rejection Control for Python
Home-page: https://github.com/onguntoglu/pyadrc
Author: Ongun Türkcüoglu
Author-email: onguntoglu@gmail.com
License: MIT license
Keywords: pyadrc
Platform: UNKNOWN
Classifier: Intended Audience :: Developers
Classifier: License :: OSI Approved :: MIT License
Classifier: Natural Language :: English
Classifier: Programming Language :: Python :: 3
Classifier: Programming Language :: Python :: 3.5
Classifier: Programming Language :: Python :: 3.6
Classifier: Programming Language :: Python :: 3.7
Classifier: Programming Language :: Python :: 3.8
Requires-Python: >=3.5
Requires-Dist: numpy
Requires-Dist: scipy
